<canvas>

<notes>

    <note id="title">
        <x>680</x>
        <y>300</y>
    </note>

    <note id="parents">
        <x>-150</x>
        <y>-100</y>
        <width>300</width>
        <height>200</height>
    </note>

<note id="1" class="pageLink" pageID="190" type="parent"><x>0</x><y>0</y><content>testing</content></note><note id="7" class="imagePageLink" pageID="669" type="child"><x>925</x><y>231</y><content>zeec</content><image>bob-dylan-auction-handwritten-lyrics-the-times-they-are-a-changin.jpg</image><image_id>1285</image_id><width>199</width><height>147</height></note><note id="8" class="note"><x>820</x><y>549</y><content>e</content></note><note id="10" class="note"><x>419</x><y>499</y><content>new content</content></note><note id="11" class="note"><x>552</x><y>617</y><content>new content</content></note><note id="12" class="imageLink"><x>994</x><y>562</y><width>263</width><height>167</height><name>youtube-okR9bmT3fnw.jpg</name><image_id>1283</image_id><link>https://www.youtube.com/watch?v=okR9bmT3fnw</link></note><note id="13" class="imagePageLink"><x>612</x><y>406</y><content>new content</content><css>color: blue;</css><image>bob-dylan-auction-handwritten-lyrics-the-times-they-are-a-changin.jpg</image><image_id>1284</image_id><width>100</width><height>50</height></note></notes>

<meta>
    <biggest_id>13</biggest_id>
    <type/>
</meta>

<connexions><connexion id_1="10" id_2="11"/></connexions></canvas>
