<canvas>

<notes>

    <note id="title">
        <x>680</x>
        <y>300</y>
    </note>

    <note id="parents">
        <x>-80</x>
        <y>-108</y>
        <width>300</width>
        <height>200</height>
    </note>

<note id="2" class="note"><x>480</x><y>464</y><content>&lt;div style="text-align: right;"&gt;&lt;span style="background-color: inherit;"&gt;--&amp;gt; the easiest is probably to&lt;font color="#000000" face="Arial"&gt;&lt;span style="font-size: 13.3333px;"&gt;&amp;nbsp;&lt;b&gt;buy it&lt;/b&gt;&lt;/span&gt;&lt;/font&gt;&lt;/span&gt;&lt;/div&gt;</content></note><note id="3" class="note"><x>511</x><y>527</y><content>for a price around : &lt;b&gt;300&#8364;&lt;/b&gt;</content></note><note id="4" class="note"><x>495</x><y>425</y><content>rental : around 50&#8364;/ month</content></note><note id="5" class="image"><x>902</x><y>260</y><width>120</width><height>182</height><name>Screenshot_2020-09-02_at_17.25.54.png</name><image_id>897</image_id></note><note id="6" class="note"><x>542</x><y>576</y><content>--&amp;gt; amortissement sur un an : &lt;b&gt;25&#8364; / mois&lt;/b&gt;</content></note><note id="7" class="pageLink" type="parent" pageID="520"><content>Office Expenses</content><x>61</x><y>40</y></note></notes>

<meta>
    <biggest_id>7</biggest_id>
    <type/>
</meta>

</canvas>
