<canvas>

<notes>

    <note id="title">
        <x>680</x>
        <y>300</y>
    </note>

    <note id="parents">
        <x>-117</x>
        <y>-158</y>
        <width>300</width>
        <height>200</height>
    </note>

<note id="2" class="note"><x>259</x><y>603</y><content>comportements que j ai :&lt;div&gt;&lt;br&gt;&lt;/div&gt;&lt;div&gt;je suis en train de parler &#224; quelqu un de proche. Je pose une question, il ou elle commence &#224; parler et je d&#233;croche et pense &#224; ma vie, &#224; un des probl&#232;mes dans ma vie&lt;/div&gt;&lt;div&gt;&lt;br&gt;&lt;/div&gt;&lt;div&gt;j ai du mal &#224; m affirmer sur un terrain de foot&lt;/div&gt;</content></note><note id="3" class="pageLink" type="parent" pageID="562"><content>sant&#233;</content><x>192</x><y>51</y></note><note id="4" class="note"><x>616</x><y>389</y><content>il faut que j\'aille voir un psy&lt;div&gt;pour parler de mes probl&#232;mes&lt;/div&gt;</content></note><note id="5" class="note"><x>891</x><y>405</y><content>je suis dans l\'attente de ce qui va se passer quand ...</content></note><note id="6" class="note"><x>871</x><y>479</y><content>je trouve que je n\'ai pas de personnalit&#233;</content></note><note id="7" class="pageLink" type="parent" pageID="523"><content>my life</content><x>59</x><y>82</y></note><note id="8" class="note"><x>281</x><y>500</y><content>in group converstions (and even in general) :&lt;div&gt;i can\'t access memories related to what we\'re talking about&lt;/div&gt;&lt;div&gt;i don\'t have the "ah &#231;a me fait penser &#224; ..."&lt;/div&gt;&lt;div&gt;&lt;br&gt;&lt;/div&gt;&lt;div&gt;sometimes, not always, depending on who i\'m with&lt;/div&gt;</content></note></notes>

<meta>
    <biggest_id>8</biggest_id>
    <type/>
</meta>

</canvas>
